crypthon/__init__.py
crypthon/crypthon.py
crypthon/obsfus.py
crypthon/setup.py
crypthon-1.0.1.dist-info/LICENSE.txt
crypthon-1.0.1.dist-info/METADATA
crypthon-1.0.1.dist-info/WHEEL
crypthon-1.0.1.dist-info/top_level.txt
crypthon-1.0.1.dist-info/RECORD
