Metadata-Version: 2.1
Name: crypthon
Version: 1.0.1
Summary: python command line tool that helps sharing and storing securely python source code files thanks to a simple and yet very strong and resilient string encryption. It also provides an obsfucation with decryption at runtime.
Home-page: https://github.com/GildaRech/crypthon
Author: Gilda Rech BANSIMBA
Author-email: bansimbagilda@gmail.com
License: UNKNOWN
Project-URL: Bug Tracker, https://github.com/GildaRech/crypthon/issues
Platform: UNKNOWN
Classifier: Programming Language :: Python :: 3
Classifier: License :: OSI Approved :: BSD License
Classifier: Operating System :: OS Independent
Requires-Python: >=3.6
License-File: LICENSE.txt
